kcidev/__init__.py
kcidev/_data/kci-dev.toml.example
kcidev/libs/__init__.py
kcidev/libs/common.py
kcidev/libs/dashboard.py
kcidev/libs/files.py
kcidev/libs/filter_options.py
kcidev/libs/filters.py
kcidev/libs/git_repo.py
kcidev/libs/job_filters.py
kcidev/libs/maestro_common.py
kcidev/main.py
kcidev/subcommands/__init__.py
kcidev/subcommands/bisect.py
kcidev/subcommands/checkout.py
kcidev/subcommands/commit.py
kcidev/subcommands/config.py
kcidev/subcommands/maestro/__init__.py
kcidev/subcommands/maestro/results.py
kcidev/subcommands/maestro/validate/__init__.py
kcidev/subcommands/maestro/validate/boots.py
kcidev/subcommands/maestro/validate/builds.py
kcidev/subcommands/maestro/validate/helper.py
kcidev/subcommands/results/__init__.py
kcidev/subcommands/results/hardware.py
kcidev/subcommands/results/options.py
kcidev/subcommands/results/parser.py
kcidev/subcommands/testretry.py
kcidev/subcommands/watch.py
kci_dev-0.1.9.dist-info/METADATA
kci_dev-0.1.9.dist-info/WHEEL
kci_dev-0.1.9.dist-info/entry_points.txt
kci_dev-0.1.9.dist-info/licenses/LICENSE
kci_dev-0.1.9.dist-info/RECORD
