Metadata-Version: 2.4
Name: kci-dev
Version: 0.1.9
Summary: Stand alone tool for Linux Kernel developers and maintainers to interact with KernelCI
License: LGPL-2.1-or-later
License-File: LICENSE
Author: Arisu Tachibana
Author-email: arisu.tachibana@miraclelinux.com
Requires-Python: >=3.10,<4.0
Classifier: Development Status :: 4 - Beta
Classifier: Environment :: Console
Classifier: Intended Audience :: Developers
Classifier: License :: OSI Approved
Classifier: Operating System :: OS Independent
Classifier: Programming Language :: Python
Classifier: Programming Language :: Python :: 3
Classifier: Programming Language :: Python :: 3.10
Classifier: Programming Language :: Python :: 3.11
Classifier: Programming Language :: Python :: 3.12
Classifier: Programming Language :: Python :: 3.13
Classifier: Programming Language :: Python :: 3.14
Classifier: Programming Language :: Python :: Implementation :: CPython
Classifier: Programming Language :: Python :: Implementation :: PyPy
Classifier: Topic :: Software Development
Classifier: Topic :: Software Development :: Libraries
Requires-Dist: click (>=8.0.0,<8.3.0)
Requires-Dist: gitpython (>=3.1.43,<4.0.0)
Requires-Dist: matplotlib (>=3.6)
Requires-Dist: mplcursors (>=0.6)
Requires-Dist: pyyaml (>=6.0.2,<7.0.0)
Requires-Dist: requests (>=2.32.3,<3.0.0)
Requires-Dist: tabulate (==0.9.0)
Requires-Dist: tomli (>=2.2.1,<3.0.0) ; python_version < "3.11"
Project-URL: Changelog, https://github.com/kernelci/kci-dev/releases
Project-URL: Documentation, https://kci.dev
Project-URL: Issue Tracker, https://github.com/kernelci/kci-dev/issues
Project-URL: Repository, https://github.com/kernelci/kci-dev
